[
  { "id": "stanford-w-id", "schoolId": "stanford", "schoolName": "Stanford University", "gender": "womens", "division": "D1", "region": "West", "campName": "Stanford Women's Soccer Elite ID Camp", "format": "residential", "typicalMonths": "June and July (multiple sessions)", "ageRange": "Grades 9-12", "estimatedCost": "$650–$850", "registrationUrl": "https://gostanford.com/sports/womens-soccer/camps", "searchFallbackUrl": "https://www.google.com/search?q=Stanford+women+soccer+ID+camp+2026+register", "athleticsUrl": "https://gostanford.com/sports/womens-soccer", "staffTier": "S", "staffTierReason": "Stanford brand + recurring College Cup runs. Selective, draws elite ECNL/MLS NEXT recruits.", "notes": "Multiple sessions per summer — Elite session is invitation-only after coach review. Pair with a campus visit.", "lastReviewedAt": "2026-05-02" },
  { "id": "stanford-m-id", "schoolId": "stanford", "schoolName": "Stanford University", "gender": "mens", "division": "D1", "region": "West", "campName": "Stanford Men's Soccer ID Camp", "format": "residential", "typicalMonths": "June and July", "ageRange": "Grades 9-12", "estimatedCost": "$650–$850", "registrationUrl": "https://gostanford.com/sports/mens-soccer/camps", "searchFallbackUrl": "https://www.google.com/search?q=Stanford+men+soccer+ID+camp+2026+register", "athleticsUrl": "https://gostanford.com/sports/mens-soccer", "staffTier": "S", "staffTierReason": "Top academic + soccer combo on the men's side. Coaches recruit from this camp directly.", "notes": "Cardinal Stadium hosts. Selective entry — submit highlight reel with app.", "lastReviewedAt": "2026-05-02" },
  { "id": "unc-w-id", "schoolId": "unc", "schoolName": "University of North Carolina", "gender": "womens", "division": "D1", "region": "Southeast", "campName": "UNC Women's Soccer Elite ID Camp", "format": "residential", "typicalMonths": "June and July (3 sessions)", "ageRange": "Grades 9-12", "estimatedCost": "$575–$725", "registrationUrl": "https://goheels.com/sports/womens-soccer/camps", "searchFallbackUrl": "https://www.google.com/search?q=UNC+women+soccer+ID+camp+2026+register", "athleticsUrl": "https://goheels.com/sports/womens-soccer", "staffTier": "S", "staffTierReason": "21 NCAA national titles. The most established women's ID camp in the country.", "notes": "Elite session is invitation-only. Prospect sessions open registration. Anson Dorrance's blueprint still drives the camp.", "lastReviewedAt": "2026-05-02" },
  { "id": "unc-m-id", "schoolId": "unc", "schoolName": "University of North Carolina", "gender": "mens", "division": "D1", "region": "Southeast", "campName": "UNC Men's Soccer ID Camp", "format": "residential", "typicalMonths": "June and July", "ageRange": "Grades 9-12", "estimatedCost": "$525–$675", "registrationUrl": "https://goheels.com/sports/mens-soccer/camps", "searchFallbackUrl": "https://www.google.com/search?q=UNC+men+soccer+ID+camp+2026+register", "athleticsUrl": "https://goheels.com/sports/mens-soccer", "staffTier": "A", "staffTierReason": "Strong ACC recruiting pipeline; not as dominant as the women's side but still top-tier.", "notes": "Carmichael Field. Two sessions per summer. ACC-style fitness emphasis.", "lastReviewedAt": "2026-05-02" },
  { "id": "ucla-w-id", "schoolId": "ucla", "schoolName": "UCLA", "gender": "womens", "division": "D1", "region": "West", "campName": "UCLA Women's Soccer ID Camp", "format": "residential", "typicalMonths": "June and July", "ageRange": "Grades 9-12", "estimatedCost": "$650–$850", "registrationUrl": "https://uclabruins.com/sports/womens-soccer/camps", "searchFallbackUrl": "https://www.google.com/search?q=UCLA+women+soccer+ID+camp+2026+register", "athleticsUrl": "https://uclabruins.com/sports/womens-soccer", "staffTier": "S", "staffTierReason": "Big Ten power; deep USWNT pipeline; elite West Coast recruiting magnet.", "notes": "Wallis Annenberg Stadium. Top recruits from California, Texas, and the Mountain West attend.", "lastReviewedAt": "2026-05-02" },
  { "id": "ucla-m-id", "schoolId": "ucla", "schoolName": "UCLA", "gender": "mens", "division": "D1", "region": "West", "campName": "UCLA Men's Soccer ID Camp", "format": "residential", "typicalMonths": "June and July", "ageRange": "Grades 9-12", "estimatedCost": "$650–$850", "registrationUrl": "https://uclabruins.com/sports/mens-soccer/camps", "searchFallbackUrl": "https://www.google.com/search?q=UCLA+men+soccer+ID+camp+2026+register", "athleticsUrl": "https://uclabruins.com/sports/mens-soccer", "staffTier": "A", "staffTierReason": "Top MLS NEXT and ECNL Boys recruiting destination on the West Coast.", "notes": "Premier MLS pipeline. Coaches use this camp to confirm offer-ready recruits.", "lastReviewedAt": "2026-05-02" },
  { "id": "usc-w-id", "schoolId": "usc", "schoolName": "University of Southern California", "gender": "womens", "division": "D1", "region": "West", "campName": "USC Women's Soccer ID Camp", "format": "residential", "typicalMonths": "June and July", "ageRange": "Grades 9-12", "estimatedCost": "$575–$725", "registrationUrl": "https://usctrojans.com/sports/womens-soccer/camps", "searchFallbackUrl": "https://www.google.com/search?q=USC+women+soccer+ID+camp+2026+register", "athleticsUrl": "https://usctrojans.com/sports/womens-soccer", "staffTier": "A", "staffTierReason": "Top LA-based women's program. Big Ten move keeps recruiting national.", "notes": "McAlister Field. Strong recruiting from California and the Southwest.", "lastReviewedAt": "2026-05-02" },
  { "id": "fsu-w-id", "schoolId": "fsu", "schoolName": "Florida State University", "gender": "womens", "division": "D1", "region": "Southeast", "campName": "FSU Women's Soccer ID Camp", "format": "residential", "typicalMonths": "June and July", "ageRange": "Grades 9-12", "estimatedCost": "$525–$695", "registrationUrl": "https://seminoles.com/sports/womens-soccer/camps", "searchFallbackUrl": "https://www.google.com/search?q=FSU+women+soccer+ID+camp+2026+register", "athleticsUrl": "https://seminoles.com/sports/womens-soccer", "staffTier": "S", "staffTierReason": "Current dynasty — multiple recent national titles. ACC powerhouse.", "notes": "One of the most well-attended camps in the Southeast. Prospect day for older recruits.", "lastReviewedAt": "2026-05-02" },
  { "id": "duke-w-id", "schoolId": "duke", "schoolName": "Duke University", "gender": "womens", "division": "D1", "region": "Southeast", "campName": "Duke Women's Soccer ID Camp", "format": "residential", "typicalMonths": "June and July", "ageRange": "Grades 9-12", "estimatedCost": "$625–$775", "registrationUrl": "https://goduke.com/sports/womens-soccer/camps", "searchFallbackUrl": "https://www.google.com/search?q=Duke+women+soccer+ID+camp+2026+register", "athleticsUrl": "https://goduke.com/sports/womens-soccer", "staffTier": "A", "staffTierReason": "Elite-academics-and-soccer pitch. High-priority for top students.", "notes": "Koskinen Stadium. Strong fit for academically driven recruits.", "lastReviewedAt": "2026-05-02" },
  { "id": "duke-m-id", "schoolId": "duke", "schoolName": "Duke University", "gender": "mens", "division": "D1", "region": "Southeast", "campName": "Duke Men's Soccer ID Camp", "format": "residential", "typicalMonths": "June and July", "ageRange": "Grades 9-12", "estimatedCost": "$625–$775", "registrationUrl": "https://goduke.com/sports/mens-soccer/camps", "searchFallbackUrl": "https://www.google.com/search?q=Duke+men+soccer+ID+camp+2026+register", "athleticsUrl": "https://goduke.com/sports/mens-soccer", "staffTier": "A", "staffTierReason": "ACC-level competition with the strongest academic pitch on the men's side.", "notes": "Koskinen Stadium. Multiple D1 commits each year out of this camp.", "lastReviewedAt": "2026-05-02" },
  { "id": "virginia-w-id", "schoolId": "virginia", "schoolName": "University of Virginia", "gender": "womens", "division": "D1", "region": "Southeast", "campName": "Virginia Women's Soccer ID Camp", "format": "residential", "typicalMonths": "June and July", "ageRange": "Grades 9-12", "estimatedCost": "$555–$695", "registrationUrl": "https://virginiasports.com/sports/womens-soccer/camps", "searchFallbackUrl": "https://www.google.com/search?q=Virginia+women+soccer+ID+camp+2026+register", "athleticsUrl": "https://virginiasports.com/sports/womens-soccer", "staffTier": "A", "staffTierReason": "Klockner Stadium. ACC academic + athletic pitch.", "notes": "Strong UVA-academic profile. Best for athletes targeting ACC + top academics.", "lastReviewedAt": "2026-05-02" },
  { "id": "virginia-m-id", "schoolId": "virginia", "schoolName": "University of Virginia", "gender": "mens", "division": "D1", "region": "Southeast", "campName": "Virginia Men's Soccer ID Camp", "format": "residential", "typicalMonths": "June and July", "ageRange": "Grades 9-12", "estimatedCost": "$555–$695", "registrationUrl": "https://virginiasports.com/sports/mens-soccer/camps", "searchFallbackUrl": "https://www.google.com/search?q=Virginia+men+soccer+ID+camp+2026+register", "athleticsUrl": "https://virginiasports.com/sports/mens-soccer", "staffTier": "S", "staffTierReason": "7 NCAA national titles. Historically dominant men's program.", "notes": "Klockner Stadium. Heavy MLS NEXT recruiting presence.", "lastReviewedAt": "2026-05-02" },
  { "id": "notredame-w-id", "schoolId": "notredame", "schoolName": "University of Notre Dame", "gender": "womens", "division": "D1", "region": "Midwest", "campName": "Notre Dame Women's Soccer ID Camp", "format": "residential", "typicalMonths": "June and July", "ageRange": "Grades 9-12", "estimatedCost": "$555–$695", "registrationUrl": "https://und.com/sports/womens-soccer/camps", "searchFallbackUrl": "https://www.google.com/search?q=Notre+Dame+women+soccer+ID+camp+2026+register", "athleticsUrl": "https://und.com/sports/womens-soccer", "staffTier": "A", "staffTierReason": "ACC + national academic brand. Strong faith-based recruit pipeline.", "notes": "Alumni Stadium. Faith-based culture with elite athletic standards.", "lastReviewedAt": "2026-05-02" },
  { "id": "notredame-m-id", "schoolId": "notredame", "schoolName": "University of Notre Dame", "gender": "mens", "division": "D1", "region": "Midwest", "campName": "Notre Dame Men's Soccer ID Camp", "format": "residential", "typicalMonths": "June and July", "ageRange": "Grades 9-12", "estimatedCost": "$555–$695", "registrationUrl": "https://und.com/sports/mens-soccer/camps", "searchFallbackUrl": "https://www.google.com/search?q=Notre+Dame+men+soccer+ID+camp+2026+register", "athleticsUrl": "https://und.com/sports/mens-soccer", "staffTier": "A", "staffTierReason": "2013 NCAA champion. ACC competition with national recruiting reach.", "notes": "Alumni Stadium. Strong Midwest + faith-based recruit base.", "lastReviewedAt": "2026-05-02" },
  { "id": "pennstate-w-id", "schoolId": "pennstate", "schoolName": "Penn State University", "gender": "womens", "division": "D1", "region": "Northeast", "campName": "Penn State Women's Soccer ID Camp", "format": "residential", "typicalMonths": "June and July", "ageRange": "Grades 9-12", "estimatedCost": "$525–$695", "registrationUrl": "https://gopsusports.com/sports/womens-soccer/camps", "searchFallbackUrl": "https://www.google.com/search?q=Penn+State+women+soccer+ID+camp+2026+register", "athleticsUrl": "https://gopsusports.com/sports/womens-soccer", "staffTier": "S", "staffTierReason": "USWNT pipeline. 2015 NCAA champion. Big Ten power.", "notes": "Jeffrey Field. One of the elite Big Ten programs.", "lastReviewedAt": "2026-05-02" },
  { "id": "wakeforest-w-id", "schoolId": "wakeforest", "schoolName": "Wake Forest University", "gender": "womens", "division": "D1", "region": "Southeast", "campName": "Wake Forest Women's Soccer ID Camp", "format": "residential", "typicalMonths": "June and July", "ageRange": "Grades 9-12", "estimatedCost": "$495–$650", "registrationUrl": "https://godeacs.com/sports/womens-soccer/camps", "searchFallbackUrl": "https://www.google.com/search?q=Wake+Forest+women+soccer+ID+camp+2026+register", "athleticsUrl": "https://godeacs.com/sports/womens-soccer", "staffTier": "A", "staffTierReason": "Strong academic + ACC athletic combination.", "notes": "Spry Stadium. Smaller-school feel with ACC-level competition.", "lastReviewedAt": "2026-05-02" },
  { "id": "wakeforest-m-id", "schoolId": "wakeforest", "schoolName": "Wake Forest University", "gender": "mens", "division": "D1", "region": "Southeast", "campName": "Wake Forest Men's Soccer ID Camp", "format": "residential", "typicalMonths": "June and July", "ageRange": "Grades 9-12", "estimatedCost": "$525–$695", "registrationUrl": "https://godeacs.com/sports/mens-soccer/camps", "searchFallbackUrl": "https://www.google.com/search?q=Wake+Forest+men+soccer+ID+camp+2026+register", "athleticsUrl": "https://godeacs.com/sports/mens-soccer", "staffTier": "S", "staffTierReason": "Top-5 men's program of the past decade. 2007 NCAA champions, multiple Final Fours.", "notes": "Spry Stadium ID camp is heavily attended. Top draft pipeline (MLS).", "lastReviewedAt": "2026-05-02" },
  { "id": "florida-w-id", "schoolId": "florida", "schoolName": "University of Florida", "gender": "womens", "division": "D1", "region": "Southeast", "campName": "Florida Gators Women's Soccer ID Camp", "format": "residential", "typicalMonths": "June and July", "ageRange": "Grades 9-12", "estimatedCost": "$495–$650", "registrationUrl": "https://floridagators.com/sports/womens-soccer/camps", "searchFallbackUrl": "https://www.google.com/search?q=Florida+Gators+women+soccer+ID+camp+2026+register", "athleticsUrl": "https://floridagators.com/sports/womens-soccer", "staffTier": "A", "staffTierReason": "1998 NCAA champion. SEC competition.", "notes": "Donald R. Dizney Stadium. Strong Florida and Southeast recruit base.", "lastReviewedAt": "2026-05-02" },
  { "id": "vanderbilt-w-id", "schoolId": "vanderbilt", "schoolName": "Vanderbilt University", "gender": "womens", "division": "D1", "region": "Southeast", "campName": "Vanderbilt Women's Soccer ID Camp", "format": "residential", "typicalMonths": "June and July", "ageRange": "Grades 9-12", "estimatedCost": "$525–$695", "registrationUrl": "https://vucommodores.com/sports/womens-soccer/camps", "searchFallbackUrl": "https://www.google.com/search?q=Vanderbilt+women+soccer+ID+camp+2026+register", "athleticsUrl": "https://vucommodores.com/sports/womens-soccer", "staffTier": "A", "staffTierReason": "Elite academics + SEC athletics. Strong fit for top students.", "notes": "Vanderbilt Soccer/Lacrosse Complex. Smaller program with SEC schedule.", "lastReviewedAt": "2026-05-02" },
  { "id": "georgetown-w-id", "schoolId": "georgetown", "schoolName": "Georgetown University", "gender": "womens", "division": "D1", "region": "Northeast", "campName": "Georgetown Women's Soccer ID Camp", "format": "residential", "typicalMonths": "June and July", "ageRange": "Grades 9-12", "estimatedCost": "$495–$650", "registrationUrl": "https://guhoyas.com/sports/womens-soccer/camps", "searchFallbackUrl": "https://www.google.com/search?q=Georgetown+women+soccer+ID+camp+2026+register", "athleticsUrl": "https://guhoyas.com/sports/womens-soccer", "staffTier": "A", "staffTierReason": "Big East academic + soccer combo.", "notes": "Shaw Field. Elite academic profile.", "lastReviewedAt": "2026-05-02" },
  { "id": "georgetown-m-id", "schoolId": "georgetown", "schoolName": "Georgetown University", "gender": "mens", "division": "D1", "region": "Northeast", "campName": "Georgetown Men's Soccer ID Camp", "format": "residential", "typicalMonths": "June and July", "ageRange": "Grades 9-12", "estimatedCost": "$495–$650", "registrationUrl": "https://guhoyas.com/sports/mens-soccer/camps", "searchFallbackUrl": "https://www.google.com/search?q=Georgetown+men+soccer+ID+camp+2026+register", "athleticsUrl": "https://guhoyas.com/sports/mens-soccer", "staffTier": "A", "staffTierReason": "2019 NCAA champion. Elite academic + Big East athletics.", "notes": "Shaw Field. One of the top academic + soccer combos in D1.", "lastReviewedAt": "2026-05-02" },
  { "id": "michigan-w-id", "schoolId": "michigan", "schoolName": "University of Michigan", "gender": "womens", "division": "D1", "region": "Midwest", "campName": "Michigan Women's Soccer ID Camp", "format": "residential", "typicalMonths": "June and July", "ageRange": "Grades 9-12", "estimatedCost": "$495–$650", "registrationUrl": "https://mgoblue.com/sports/womens-soccer/camps", "searchFallbackUrl": "https://www.google.com/search?q=Michigan+women+soccer+ID+camp+2026+register", "athleticsUrl": "https://mgoblue.com/sports/womens-soccer", "staffTier": "A", "staffTierReason": "Big Ten power; rising program with strong recent recruiting classes.", "notes": "U-M Soccer Stadium. Big Ten profile + strong academics.", "lastReviewedAt": "2026-05-02" },
  { "id": "northwestern-w-id", "schoolId": "northwestern", "schoolName": "Northwestern University", "gender": "womens", "division": "D1", "region": "Midwest", "campName": "Northwestern Women's Soccer ID Camp", "format": "residential", "typicalMonths": "June and July", "ageRange": "Grades 9-12", "estimatedCost": "$495–$650", "registrationUrl": "https://nusports.com/sports/womens-soccer/camps", "searchFallbackUrl": "https://www.google.com/search?q=Northwestern+women+soccer+ID+camp+2026+register", "athleticsUrl": "https://nusports.com/sports/womens-soccer", "staffTier": "A", "staffTierReason": "Top Big Ten academic + soccer combo.", "notes": "Lakeside Field. One of the strongest Big Ten academic options.", "lastReviewedAt": "2026-05-02" },
  { "id": "portland-w-id", "schoolId": "portland", "schoolName": "University of Portland", "gender": "womens", "division": "D1", "region": "West", "campName": "Portland Pilots Women's Soccer ID Camp", "format": "residential", "typicalMonths": "June and July", "ageRange": "Grades 9-12", "estimatedCost": "$425–$575", "registrationUrl": "https://portlandpilots.com/sports/womens-soccer/camps", "searchFallbackUrl": "https://www.google.com/search?q=Portland+Pilots+women+soccer+ID+camp+2026+register", "athleticsUrl": "https://portlandpilots.com/sports/womens-soccer", "staffTier": "A", "staffTierReason": "2002 and 2005 NCAA champions. Megan Rapinoe / Christine Sinclair pipeline.", "notes": "Merlo Field. Strong WCC program with deep USWNT alumni list.", "lastReviewedAt": "2026-05-02" },
  { "id": "santaclara-w-id", "schoolId": "santaclara", "schoolName": "Santa Clara University", "gender": "womens", "division": "D1", "region": "West", "campName": "Santa Clara Women's Soccer ID Camp", "format": "residential", "typicalMonths": "June and July", "ageRange": "Grades 9-12", "estimatedCost": "$425–$575", "registrationUrl": "https://santaclarabroncos.com/sports/womens-soccer/camps", "searchFallbackUrl": "https://www.google.com/search?q=Santa+Clara+women+soccer+ID+camp+2026+register", "athleticsUrl": "https://santaclarabroncos.com/sports/womens-soccer", "staffTier": "A", "staffTierReason": "2001 NCAA champion. Brandi Chastain's alma mater. WCC contender.", "notes": "Buck Shaw Stadium. Strong Bay Area academic + soccer fit.", "lastReviewedAt": "2026-05-02" },
  { "id": "tennessee-w-id", "schoolId": "tennessee", "schoolName": "University of Tennessee", "gender": "womens", "division": "D1", "region": "Southeast", "campName": "Tennessee Women's Soccer ID Camp", "format": "residential", "typicalMonths": "June and July", "ageRange": "Grades 9-12", "estimatedCost": "$425–$575", "registrationUrl": "https://utsports.com/sports/womens-soccer/camps", "searchFallbackUrl": "https://www.google.com/search?q=Tennessee+women+soccer+ID+camp+2026+register", "athleticsUrl": "https://utsports.com/sports/womens-soccer", "staffTier": "B", "staffTierReason": "Solid SEC program. Less marquee than FSU/Florida but real opportunities.", "notes": "Regal Soccer Stadium. SEC competition with strong Southeast recruit base.", "lastReviewedAt": "2026-05-02" },

  { "id": "indiana-m-id", "schoolId": "indiana", "schoolName": "Indiana University", "gender": "mens", "division": "D1", "region": "Midwest", "campName": "Indiana Hoosiers Men's Soccer ID Camp", "format": "residential", "typicalMonths": "June and July", "ageRange": "Grades 9-12", "estimatedCost": "$495–$650", "registrationUrl": "https://iuhoosiers.com/sports/mens-soccer/camps", "searchFallbackUrl": "https://www.google.com/search?q=Indiana+Hoosiers+men+soccer+ID+camp+2026+register", "athleticsUrl": "https://iuhoosiers.com/sports/mens-soccer", "staffTier": "S", "staffTierReason": "8 NCAA national titles — most successful men's program in NCAA history.", "notes": "Bill Armstrong Stadium. Top MLS pipeline. Coaches recruit nationally.", "lastReviewedAt": "2026-05-02" },
  { "id": "maryland-m-id", "schoolId": "maryland", "schoolName": "University of Maryland", "gender": "mens", "division": "D1", "region": "Northeast", "campName": "Maryland Terrapins Men's Soccer ID Camp", "format": "residential", "typicalMonths": "June and July", "ageRange": "Grades 9-12", "estimatedCost": "$495–$650", "registrationUrl": "https://umterps.com/sports/mens-soccer/camps", "searchFallbackUrl": "https://www.google.com/search?q=Maryland+Terrapins+men+soccer+ID+camp+2026+register", "athleticsUrl": "https://umterps.com/sports/mens-soccer", "staffTier": "A", "staffTierReason": "3 NCAA national titles. Big Ten program with elite MLS pipeline.", "notes": "Ludwig Field. Multiple MLS first-round draft picks each year.", "lastReviewedAt": "2026-05-02" },
  { "id": "akron-m-id", "schoolId": "akron", "schoolName": "University of Akron", "gender": "mens", "division": "D1", "region": "Midwest", "campName": "Akron Zips Men's Soccer ID Camp", "format": "residential", "typicalMonths": "June and July", "ageRange": "Grades 9-12", "estimatedCost": "$425–$595", "registrationUrl": "https://gozips.com/sports/mens-soccer/camps", "searchFallbackUrl": "https://www.google.com/search?q=Akron+men+soccer+ID+camp+2026+register", "athleticsUrl": "https://gozips.com/sports/mens-soccer", "staffTier": "A", "staffTierReason": "2010 NCAA champion. Top MLS draft pipeline; produces 1st-round picks.", "notes": "FirstEnergy Stadium. MAC program but recruits nationally.", "lastReviewedAt": "2026-05-02" },
  { "id": "slu-m-id", "schoolId": "slu", "schoolName": "Saint Louis University", "gender": "mens", "division": "D1", "region": "Midwest", "campName": "SLU Billikens Men's Soccer ID Camp", "format": "residential", "typicalMonths": "June and July", "ageRange": "Grades 9-12", "estimatedCost": "$425–$595", "registrationUrl": "https://slubillikens.com/sports/mens-soccer/camps", "searchFallbackUrl": "https://www.google.com/search?q=Saint+Louis+University+men+soccer+ID+camp+2026+register", "athleticsUrl": "https://slubillikens.com/sports/mens-soccer", "staffTier": "A", "staffTierReason": "10 NCAA national titles — most in NCAA men's history.", "notes": "Hermann Stadium. Historic A-10 program.", "lastReviewedAt": "2026-05-02" },
  { "id": "ucsb-m-id", "schoolId": "ucsb", "schoolName": "UC Santa Barbara", "gender": "mens", "division": "D1", "region": "West", "campName": "UCSB Gauchos Men's Soccer ID Camp", "format": "residential", "typicalMonths": "June and July", "ageRange": "Grades 9-12", "estimatedCost": "$495–$650", "registrationUrl": "https://ucsbgauchos.com/sports/mens-soccer/camps", "searchFallbackUrl": "https://www.google.com/search?q=UCSB+men+soccer+ID+camp+2026+register", "athleticsUrl": "https://ucsbgauchos.com/sports/mens-soccer", "staffTier": "A", "staffTierReason": "2006 NCAA champion. Top California exposure.", "notes": "Harder Stadium has the largest college soccer crowds in the country.", "lastReviewedAt": "2026-05-02" },
  { "id": "syracuse-m-id", "schoolId": "syracuse", "schoolName": "Syracuse University", "gender": "mens", "division": "D1", "region": "Northeast", "campName": "Syracuse Men's Soccer ID Camp", "format": "residential", "typicalMonths": "June and July", "ageRange": "Grades 9-12", "estimatedCost": "$495–$650", "registrationUrl": "https://cuse.com/sports/mens-soccer/camps", "searchFallbackUrl": "https://www.google.com/search?q=Syracuse+men+soccer+ID+camp+2026+register", "athleticsUrl": "https://cuse.com/sports/mens-soccer", "staffTier": "A", "staffTierReason": "2022 NCAA national champion. ACC competition.", "notes": "SU Soccer Stadium. Recent surge in recruiting following 2022 title.", "lastReviewedAt": "2026-05-02" },
  { "id": "clemson-m-id", "schoolId": "clemson", "schoolName": "Clemson University", "gender": "mens", "division": "D1", "region": "Southeast", "campName": "Clemson Tigers Men's Soccer ID Camp", "format": "residential", "typicalMonths": "June and July", "ageRange": "Grades 9-12", "estimatedCost": "$495–$650", "registrationUrl": "https://clemsontigers.com/sports/mens-soccer/camps", "searchFallbackUrl": "https://www.google.com/search?q=Clemson+Tigers+men+soccer+ID+camp+2026+register", "athleticsUrl": "https://clemsontigers.com/sports/mens-soccer", "staffTier": "A", "staffTierReason": "3 NCAA national titles. Recent ACC contender.", "notes": "Historic Riggs Field. Strong ACC + Southeast recruiting base.", "lastReviewedAt": "2026-05-02" },

  { "id": "denver-w-id", "schoolId": "denver", "schoolName": "University of Denver", "gender": "womens", "division": "D1", "region": "Southwest", "campName": "Denver Pioneers Women's Soccer ID Camp", "format": "residential", "typicalMonths": "June and July", "ageRange": "Grades 9-12", "estimatedCost": "$425–$575", "registrationUrl": "https://denverpioneers.com/sports/womens-soccer/camps", "searchFallbackUrl": "https://www.google.com/search?q=University+of+Denver+women+soccer+ID+camp+2026+register", "athleticsUrl": "https://denverpioneers.com/sports/womens-soccer", "staffTier": "B", "staffTierReason": "Solid Summit League program with strong academic profile.", "notes": "CIBER Field. Mountain altitude training; Summit League competition.", "lastReviewedAt": "2026-05-02" },
  { "id": "byu-w-id", "schoolId": "byu", "schoolName": "Brigham Young University", "gender": "womens", "division": "D1", "region": "Southwest", "campName": "BYU Cougars Women's Soccer ID Camp", "format": "residential", "typicalMonths": "June and July", "ageRange": "Grades 9-12", "estimatedCost": "$395–$525", "registrationUrl": "https://byucougars.com/sports/womens-soccer/camps", "searchFallbackUrl": "https://www.google.com/search?q=BYU+women+soccer+ID+camp+2026+register", "athleticsUrl": "https://byucougars.com/sports/womens-soccer", "staffTier": "B", "staffTierReason": "Big 12 program with strong faith-based recruit fit.", "notes": "South Field. Faith-based culture (Honor Code applies).", "lastReviewedAt": "2026-05-02" },

  { "id": "tampa-id", "schoolId": "tampa", "schoolName": "University of Tampa", "gender": "both", "division": "D2", "region": "Southeast", "campName": "Tampa Spartans Soccer ID Camp", "format": "residential", "typicalMonths": "June and July", "ageRange": "Grades 9-12", "estimatedCost": "$295–$425", "registrationUrl": "https://tampaspartans.com/sports/soccer/camps", "searchFallbackUrl": "https://www.google.com/search?q=University+of+Tampa+soccer+ID+camp+2026+register", "athleticsUrl": "https://tampaspartans.com", "staffTier": "A", "staffTierReason": "D2 SSC powerhouse for both programs. Multiple recent national titles.", "notes": "Pepin/Rood Stadium. Top D2 destination in the Southeast.", "lastReviewedAt": "2026-05-02" },
  { "id": "rollins-id", "schoolId": "rollins", "schoolName": "Rollins College", "gender": "both", "division": "D2", "region": "Southeast", "campName": "Rollins Tars Soccer ID Camp", "format": "day", "typicalMonths": "June and July", "ageRange": "Grades 9-12", "estimatedCost": "$195–$295", "registrationUrl": "https://rollinssports.com/sports/soccer/camps", "searchFallbackUrl": "https://www.google.com/search?q=Rollins+College+soccer+ID+camp+2026+register", "athleticsUrl": "https://rollinssports.com", "staffTier": "C", "staffTierReason": "Liberal arts D2 program in Florida. Solid SSC competition.", "notes": "Cahall-Sandspur Field. Good academic + D2 fit.", "lastReviewedAt": "2026-05-02" },
  { "id": "gvsu-id", "schoolId": "gvsu", "schoolName": "Grand Valley State University", "gender": "both", "division": "D2", "region": "Midwest", "campName": "GVSU Lakers Soccer ID Camp", "format": "day", "typicalMonths": "June and July", "ageRange": "Grades 9-12", "estimatedCost": "$165–$275", "registrationUrl": "https://gvsulakers.com/sports/soccer/camps", "searchFallbackUrl": "https://www.google.com/search?q=Grand+Valley+State+soccer+ID+camp+2026+register", "athleticsUrl": "https://gvsulakers.com", "staffTier": "A", "staffTierReason": "GLIAC D2 power for women's soccer (multiple national titles).", "notes": "Lubbers Stadium. Premier D2 program in the Midwest.", "lastReviewedAt": "2026-05-02" },
  { "id": "mines-id", "schoolId": "mines", "schoolName": "Colorado School of Mines", "gender": "both", "division": "D2", "region": "Southwest", "campName": "Mines Orediggers Soccer ID Camp", "format": "day", "typicalMonths": "June and July", "ageRange": "Grades 9-12", "estimatedCost": "$185–$295", "registrationUrl": "https://minesathletics.com/sports/soccer/camps", "searchFallbackUrl": "https://www.google.com/search?q=Colorado+School+of+Mines+soccer+ID+camp+2026+register", "athleticsUrl": "https://minesathletics.com", "staffTier": "C", "staffTierReason": "Top engineering academics. RMAC D2 competition.", "notes": "Marv Kay Stadium. Excellent fit for engineering-focused recruits.", "lastReviewedAt": "2026-05-02" },
  { "id": "westchester-id", "schoolId": "westchester", "schoolName": "West Chester University", "gender": "both", "division": "D2", "region": "Northeast", "campName": "West Chester Golden Rams Soccer ID Camp", "format": "day", "typicalMonths": "June and July", "ageRange": "Grades 9-12", "estimatedCost": "$155–$265", "registrationUrl": "https://wcugoldenrams.com/sports/soccer/camps", "searchFallbackUrl": "https://www.google.com/search?q=West+Chester+University+soccer+ID+camp+2026+register", "athleticsUrl": "https://wcugoldenrams.com", "staffTier": "C", "staffTierReason": "PSAC D2 program — both teams are nationally competitive.", "notes": "Located near Philadelphia. Strong academic + D2 combo.", "lastReviewedAt": "2026-05-02" },

  { "id": "williams-prospect", "schoolId": "williams", "schoolName": "Williams College", "gender": "both", "division": "D3", "region": "Northeast", "campName": "Williams Ephs Soccer Prospect Day", "format": "prospect-day", "typicalMonths": "August and October", "ageRange": "Grades 11-12", "estimatedCost": "$65–$125", "registrationUrl": "https://ephsports.com/sports/soccer/camps", "searchFallbackUrl": "https://www.google.com/search?q=Williams+College+soccer+prospect+day+2026+register", "athleticsUrl": "https://ephsports.com", "staffTier": "B", "staffTierReason": "NESCAC #1 academic program. D3 cannot run paid ID camps the way D1 can — this is a prospect day.", "notes": "Cole Field. NESCAC top academics; prospect day for serious recruits.", "lastReviewedAt": "2026-05-02" },
  { "id": "amherst-prospect", "schoolId": "amherst", "schoolName": "Amherst College", "gender": "both", "division": "D3", "region": "Northeast", "campName": "Amherst Mammoths Soccer Prospect Day", "format": "prospect-day", "typicalMonths": "August and October", "ageRange": "Grades 11-12", "estimatedCost": "$65–$125", "registrationUrl": "https://amherstathletics.com/sports/soccer/camps", "searchFallbackUrl": "https://www.google.com/search?q=Amherst+College+soccer+prospect+day+2026+register", "athleticsUrl": "https://amherstathletics.com", "staffTier": "B", "staffTierReason": "NESCAC top academics + soccer.", "notes": "Hitchcock Field. Prospect day for senior-year recruits.", "lastReviewedAt": "2026-05-02" },
  { "id": "tufts-prospect", "schoolId": "tufts", "schoolName": "Tufts University", "gender": "both", "division": "D3", "region": "Northeast", "campName": "Tufts Jumbos Soccer Prospect Day", "format": "prospect-day", "typicalMonths": "August and October", "ageRange": "Grades 11-12", "estimatedCost": "$75–$135", "registrationUrl": "https://gotuftsjumbos.com/sports/soccer/camps", "searchFallbackUrl": "https://www.google.com/search?q=Tufts+University+soccer+prospect+day+2026+register", "athleticsUrl": "https://gotuftsjumbos.com", "staffTier": "A", "staffTierReason": "Multiple D3 men's national titles (2014, 2016, 2018). Top NESCAC program.", "notes": "Kraft Field. Hosts the combined NESCAC ID combine — very high leverage.", "lastReviewedAt": "2026-05-02" },
  { "id": "jhu-prospect", "schoolId": "jhu", "schoolName": "Johns Hopkins University", "gender": "both", "division": "D3", "region": "Northeast", "campName": "Johns Hopkins Blue Jays Soccer Prospect Day", "format": "prospect-day", "typicalMonths": "August and October", "ageRange": "Grades 11-12", "estimatedCost": "$65–$125", "registrationUrl": "https://hopkinssports.com/sports/soccer/camps", "searchFallbackUrl": "https://www.google.com/search?q=Johns+Hopkins+soccer+prospect+day+2026+register", "athleticsUrl": "https://hopkinssports.com", "staffTier": "C", "staffTierReason": "Centennial Conference D3. Premier academic profile.", "notes": "JHU Homewood Field. Strong fit for pre-med-track athletes.", "lastReviewedAt": "2026-05-02" },
  { "id": "pomona-prospect", "schoolId": "pomona", "schoolName": "Pomona-Pitzer Colleges", "gender": "both", "division": "D3", "region": "West", "campName": "Pomona-Pitzer Sagehens Soccer Prospect Day", "format": "prospect-day", "typicalMonths": "August and October", "ageRange": "Grades 11-12", "estimatedCost": "$75–$135", "registrationUrl": "https://sagehens.com/sports/soccer/camps", "searchFallbackUrl": "https://www.google.com/search?q=Pomona-Pitzer+soccer+prospect+day+2026+register", "athleticsUrl": "https://sagehens.com", "staffTier": "C", "staffTierReason": "SCIAC D3 prospect day — combined Pomona + Pitzer roster.", "notes": "Strehle Field. Top Claremont Colleges soccer program.", "lastReviewedAt": "2026-05-02" },
  { "id": "emory-prospect", "schoolId": "emory", "schoolName": "Emory University", "gender": "both", "division": "D3", "region": "Southeast", "campName": "Emory Eagles Soccer Prospect Day", "format": "prospect-day", "typicalMonths": "August and October", "ageRange": "Grades 11-12", "estimatedCost": "$75–$135", "registrationUrl": "https://emoryathletics.com/sports/soccer/camps", "searchFallbackUrl": "https://www.google.com/search?q=Emory+University+soccer+prospect+day+2026+register", "athleticsUrl": "https://emoryathletics.com", "staffTier": "C", "staffTierReason": "UAA D3 program — top academic profile.", "notes": "Woodruff PE Center field. Strong men's and women's programs.", "lastReviewedAt": "2026-05-02" },
  { "id": "messiah-id", "schoolId": "messiah", "schoolName": "Messiah University", "gender": "both", "division": "D3", "region": "Northeast", "campName": "Messiah Falcons Soccer ID Camp", "format": "residential", "typicalMonths": "June and July", "ageRange": "Grades 9-12", "estimatedCost": "$295–$425", "registrationUrl": "https://messiahathletics.com/sports/soccer/camps", "searchFallbackUrl": "https://www.google.com/search?q=Messiah+University+soccer+ID+camp+2026+register", "athleticsUrl": "https://messiahathletics.com", "staffTier": "A", "staffTierReason": "Most decorated D3 men's program — 13+ NCAA national titles combined men's/women's.", "notes": "Strong faith-based culture. One of the best D3 ID camps regardless of academic tier.", "lastReviewedAt": "2026-05-02" },
  { "id": "calvin-id", "schoolId": "calvin", "schoolName": "Calvin University", "gender": "both", "division": "D3", "region": "Midwest", "campName": "Calvin Knights Soccer ID Camp", "format": "day", "typicalMonths": "June and July", "ageRange": "Grades 9-12", "estimatedCost": "$155–$245", "registrationUrl": "https://calvinknights.com/sports/soccer/camps", "searchFallbackUrl": "https://www.google.com/search?q=Calvin+University+soccer+ID+camp+2026+register", "athleticsUrl": "https://calvinknights.com", "staffTier": "B", "staffTierReason": "Top D3 program in the Midwest. MIAA conference contender.", "notes": "Christian Reformed culture; competitive MIAA program.", "lastReviewedAt": "2026-05-02" }
]
